checkrs/__init__.py
checkrs/base.py
checkrs/cont_scalars.py
checkrs/disc_scalars.py
checkrs/lowess.py
checkrs/marginal.py
checkrs/market.py
checkrs/plot_utils.py
checkrs/reliability.py
checkrs/sim_cdf.py
checkrs/sim_kde.py
checkrs/smoothers.py
checkrs/utils.py
checkrs-0.2.0.dist-info/LICENSE.txt
checkrs-0.2.0.dist-info/WHEEL
checkrs-0.2.0.dist-info/METADATA
checkrs-0.2.0.dist-info/RECORD
