Metadata-Version: 2.1
Name: checkrs
Version: 0.2.0
Summary: Tools for simulation-based model checking and diagnostics.
Home-page: https://github.com/timothyb0912/checkrs
License: UNKNOWN
Keywords: diagnostics,visualization,data-science,matplotlib
Author: Timothy Brathwaite
Author-email: timothyb0912@gmail.com
Requires-Python: >=3.3
Classifier: Topic :: Software Development :: Libraries :: Python Modules
Classifier: Topic :: Scientific/Engineering
Classifier: Intended Audience :: Science/Research
Classifier: Intended Audience :: End Users/Desktop
Classifier: Intended Audience :: Developers
Classifier: Programming Language :: Python :: 3
Classifier: Programming Language :: Python :: 3.6
Classifier: Programming Language :: Python :: 3.7
Classifier: Programming Language :: Python :: 3.8
Classifier: Environment :: Console
Classifier: Development Status :: 2 - Pre-Alpha
Classifier: License :: OSI Approved :: BSD License
Requires-Dist: altair
Requires-Dist: altair-viewer
Requires-Dist: attrs
Requires-Dist: future
Requires-Dist: matplotlib
Requires-Dist: numpy
Requires-Dist: pandas
Requires-Dist: plotnine
Requires-Dist: scipy
Requires-Dist: seaborn
Requires-Dist: scikit-learn
Requires-Dist: scipy
Requires-Dist: seaborn
Requires-Dist: statsmodels
Requires-Dist: torch
Requires-Dist: typing_extensions
Requires-Dist: tqdm
